wick_reversal/ThreeLineOrderBot.py
wick_reversal/WickReversalOrderBot.py
wick_reversal/__init__.py
wick_reversal/config.py
wick_reversal/main.py
wick_reversal/main_m.py
wick_reversal/okx_buou/Account_api.py
wick_reversal/okx_buou/Affiliate_api.py
wick_reversal/okx_buou/Broker_api.py
wick_reversal/okx_buou/Convert_api.py
wick_reversal/okx_buou/Copytrading_api.py
wick_reversal/okx_buou/FDBroker_api.py
wick_reversal/okx_buou/Finance_api.py
wick_reversal/okx_buou/Funding_api.py
wick_reversal/okx_buou/Market_api.py
wick_reversal/okx_buou/Public_api.py
wick_reversal/okx_buou/Recurring_api.py
wick_reversal/okx_buou/Rfq_api.py
wick_reversal/okx_buou/SprdApi_api.py
wick_reversal/okx_buou/Trade_api.py
wick_reversal/okx_buou/TradingBot_api.py
wick_reversal/okx_buou/TradingData_api.py
wick_reversal/okx_buou/__init__.py
wick_reversal/okx_buou/client.py
wick_reversal/okx_buou/consts.py
wick_reversal/okx_buou/exceptions.py
wick_reversal/okx_buou/status_api.py
wick_reversal/okx_buou/subAccount_api.py
wick_reversal/okx_buou/utils.py
wick_reversal/okxapi.py
wick_reversal/zhen.py.bak
wick_reversal/zhen_2.py
openfund_wick_reversal-1.3.0.dist-info/METADATA
openfund_wick_reversal-1.3.0.dist-info/WHEEL
openfund_wick_reversal-1.3.0.dist-info/entry_points.txt
openfund_wick_reversal-1.3.0.dist-info/RECORD
