Metadata-Version: 2.3
Name: openfund-wick-reversal
Version: 1.3.0
Summary: Openfund-wick-reversal:Buy on lower wick reversal,Sell on upper wick reversal.
Requires-Python: >=3.9,<4.0
Classifier: Programming Language :: Python :: 3
Classifier: Programming Language :: Python :: 3.9
Classifier: Programming Language :: Python :: 3.10
Classifier: Programming Language :: Python :: 3.11
Classifier: Programming Language :: Python :: 3.12
Classifier: Programming Language :: Python :: 3.13
Requires-Dist: ccxt (>=4.4.26,<5.0.0)
Requires-Dist: pandas (>=2.2.3,<3.0.0)
Requires-Dist: pydantic-settings (>=2.1.0,<3.0.0)
Requires-Dist: python-okx (>=0.3.5,<0.4.0)
Requires-Dist: requests (>=2.27.1,<3.0.0)
